tormail/__init__.py
tormail/listen.py
tormail/mail.py
tormail-0.0.4.dist-info/METADATA
tormail-0.0.4.dist-info/WHEEL
tormail-0.0.4.dist-info/top_level.txt
tormail-0.0.4.dist-info/RECORD
